rbxflip/__init__.py
rbxflip/errors.py
rbxflip/roulette.py
rbxflip/shop.py
rbxflip/user.py
rbxflip/utils.py
rbxflip-1.0.8.dist-info/METADATA
rbxflip-1.0.8.dist-info/WHEEL
rbxflip-1.0.8.dist-info/top_level.txt
rbxflip-1.0.8.dist-info/RECORD
